[
  {
    "id": "m1",
    "clientId": "demo-jumbo",
    "workspaceId": "ws_jumbo_customer_service",
    "name": "Liza",
    "image": "/images/client-mascots/m1-liza.png",
    "status": "Active",
    "conversations": 482,
    "description": "Customer service assistant for general inquiries",
    "metrics": {
      "responseTime": 1.2,
      "resolutionRate": 82,
      "csat": 4.5
    }
  },
  {
    "id": "m2",
    "clientId": "demo-jumbo",
    "workspaceId": "ws_jumbo_customer_service",
    "name": "Remco",
    "image": "/images/client-mascots/m2-remco.png",
    "status": "Active",
    "conversations": 324,
    "description": "Technical support specialist assistant",
    "metrics": {
      "responseTime": 0.8,
      "resolutionRate": 88,
      "csat": 4.7
    }
  },
  {
    "id": "m3",
    "clientId": "demo-jumbo",
    "workspaceId": "ws_jumbo_hr",
    "name": "Sarah",
    "image": "/images/client-mascots/m3-sarah.png",
    "status": "Active",
    "conversations": 156,
    "description": "HR assistant for internal queries",
    "metrics": {
      "responseTime": 1.0,
      "resolutionRate": 80,
      "csat": 4.6
    }
  },
  {
    "id": "m4",
    "clientId": "demo-jumbo",
    "workspaceId": "ws_jumbo_store",
    "name": "Max",
    "image": "/images/client-mascots/m4-max.png",
    "status": "Active",
    "conversations": 89,
    "description": "Store information and locator assistant",
    "metrics": {
      "responseTime": 0.5,
      "resolutionRate": 95,
      "csat": 4.9
    }
  },
  {
    "id": "m5",
    "clientId": "demo-hitapes",
    "workspaceId": "ws_techstart_main",
    "name": "Vinny",
    "image": "/images/client-mascots/m5-vinny.png",
    "status": "Active",
    "conversations": 322,
    "description": "Sales assistant and product recommendations",
    "metrics": {
      "responseTime": 0.9,
      "resolutionRate": 85,
      "csat": 4.8
    }
  },
  {
    "id": "m6",
    "clientId": "demo-hitapes",
    "workspaceId": "ws_techstart_main",
    "name": "Tech",
    "image": "/images/client-mascots/m6-tech.png",
    "status": "Paused",
    "conversations": 0,
    "description": "Technical support and troubleshooting",
    "metrics": {
      "responseTime": 0,
      "resolutionRate": 0,
      "csat": 0
    }
  }
]
